{"ufd_url":"https://ultimateframedata.com/bayonetta.php","name":"bayonetta","move_sections":[{"section_name":"Ground Attacks","html_id":"groundattacks","moves":[{"hitboxes":[{"name":null,"url":"https://ultimateframedata.com/hitboxes/bayonetta/BayonettaJab1.gif"}],"move_name":"Jab 1","startup":"9","total_frames":"31","landing_lag":null,"notes":"Transitions to jab 2 as early as frame 15","base_damage":"1.4","shield_lag":"4","shield_stun":"3","which_hitbox":null,"advantage":"\\-19","active_frames":"9—12","hops_autocancel":null,"hops_actionable":null,"endlag":"19"},{"hitboxes":[{"name":null,"url":"https://ultimateframedata.com/hitboxes/bayonetta/BayonettaJab2.gif"}],"move_name":"Jab 2","startup":"7","total_frames":"31","landing_lag":null,"notes":"Transitions to jab 3 as early as frame 14","base_damage":"1.4","shield_lag":"4","shield_stun":"3","which_hitbox":null,"advantage":"\\-21","active_frames":"7—8","hops_autocancel":null,"hops_actionable":null,"endlag":"23"},{"hitboxes":[{"name":null,"url":"https://ultimateframedata.com/hitboxes/bayonetta/BayonettaJab3.gif"}],"move_name":"Jab 3","startup":"7","total_frames":"39","landing_lag":null,"notes":"Transitions to rapid jab as early as frame 17","base_damage":"2.2","shield_lag":"6","shield_stun":"3","which_hitbox":null,"advantage":"\\-29","active_frames":"7—8","hops_autocancel":null,"hops_actionable":null,"endlag":"31"},{"hitboxes":[{"name":null,"url":"https://ultimateframedata.com/hitboxes/bayonetta/BayonettaJabRapid.gif"}],"move_name":"Rapid Jab","startup":"6/10/14","total_frames":null,"landing_lag":null,"notes":null,"base_damage":"0.5/0.2","shield_lag":"4","shield_stun":"4","which_hitbox":null,"advantage":null,"active_frames":null,"hops_autocancel":null,"hops_actionable":null,"endlag":null},{"hitboxes":[{"name":null,"url":"https://ultimateframedata.com/hitboxes/bayonetta/BayonettaJabRapidEnd.gif"}],"move_name":"Rapid Jab Finisher","startup":"4/11","total_frames":"62","landing_lag":null,"notes":null,"base_damage":"5.0","shield_lag":"10","shield_stun":"6","which_hitbox":null,"advantage":"\\-45","active_frames":"4—5/11—12","hops_autocancel":null,"hops_actionable":null,"endlag":"50"},{"hitboxes":[{"name":null,"url":"https://ultimateframedata.com/hitboxes/bayonetta/BayonettaFTilt1.gif"}],"move_name":"Forward Tilt 1","startup":"12","total_frames":"31","landing_lag":null,"notes":"Transitions to next hit as early as frame 16","base_damage":"3.0","shield_lag":"5","shield_stun":"4","which_hitbox":null,"advantage":"\\-15","active_frames":"12","hops_autocancel":null,"hops_actionable":null,"endlag":"19"},{"hitboxes":[{"name":null,"url":"https://ultimateframedata.com/hitboxes/bayonetta/BayonettaFTilt2.gif"}],"move_name":"Forward Tilt 2","startup":"12","total_frames":"39","landing_lag":null,"notes":"Transitions to next hit as early as frame 16","base_damage":"3.0","shield_lag":"5","shield_stun":"4","which_hitbox":null,"advantage":"\\-23","active_frames":"12","hops_autocancel":null,"hops_actionable":null,"endlag":"27"},{"hitboxes":[{"name":null,"url":"https://ultimateframedata.com/hitboxes/bayonetta/BayonettaFTilt3.gif"}],"move_name":"Forward Tilt 3","startup":"14","total_frames":"39","landing_lag":null,"notes":null,"base_damage":"7.0","shield_lag":"7","shield_stun":"7","which_hitbox":null,"advantage":"\\-21","active_frames":"14—15","hops_autocancel":null,"hops_actionable":null,"endlag":"24"},{"hitboxes":[{"name":null,"url":"https://ultimateframedata.com/hitboxes/bayonetta/BayonettaUTilt.gif"}],"move_name":"Up Tilt","startup":"7/10/13","total_frames":"29","landing_lag":null,"notes":null,"base_damage":"1.5/6.0","shield_lag":null,"shield_stun":"4/9","which_hitbox":"3/6","advantage":"\\-19/-10","active_frames":"7—9(10—12)/13—15","hops_autocancel":null,"hops_actionable":null,"endlag":"14"},{"hitboxes":[{"name":null,"url":"https://ultimateframedata.com/hitboxes/bayonetta/BayonettaDTilt.gif"}],"move_name":"Down Tilt","startup":"7","total_frames":"28","landing_lag":null,"notes":null,"base_damage":"5.0/6.0","shield_lag":"6/6","shield_stun":"6/6","which_hitbox":"Close/Far","advantage":"\\-15","active_frames":"7—8","hops_autocancel":null,"hops_actionable":null,"endlag":"20"},{"hitboxes":[{"name":null,"url":"https://ultimateframedata.com/hitboxes/bayonetta/BayonettaDashAttack.gif"}],"move_name":"Dash Attack","startup":"15","total_frames":"42","landing_lag":null,"notes":null,"base_damage":"10.0/8.0","shield_lag":"8/7","shield_stun":"10/8","which_hitbox":"Early/Late","advantage":"\\-17","active_frames":"15—20(21—26)","hops_autocancel":null,"hops_actionable":null,"endlag":"16"},{"hitboxes":[{"name":null,"url":"https://ultimateframedata.com/hitboxes/bayonetta/BayonettaFSmash.gif"}],"move_name":"Forward Smash","startup":"17","total_frames":"66","landing_lag":null,"notes":"Charge hold is frame 2","base_damage":"16.0/14.0","shield_lag":"14/10","shield_stun":"11/10","which_hitbox":"Far/Close","advantage":"\\-38/-39","active_frames":"17—21","hops_autocancel":null,"hops_actionable":null,"endlag":"45"},{"hitboxes":[{"name":null,"url":"https://ultimateframedata.com/hitboxes/bayonetta/BayonettaUSmash.gif"}],"move_name":"Up Smash","startup":"18","total_frames":"64","landing_lag":null,"notes":"Charge hold is frame 6","base_damage":"17.0/16.0/15.0","shield_lag":"11/10/10","shield_stun":"11/11/10","which_hitbox":"Early/Late/Later","advantage":"\\-35","active_frames":"18—19(20—21/22—23)","hops_autocancel":null,"hops_actionable":null,"endlag":"41"},{"hitboxes":[{"name":"Bayo","url":"https://ultimateframedata.com/hitboxes/bayonetta/BayonettaDSmash.gif"},{"name":"Giant Foot","url":"https://ultimateframedata.com/hitboxes/bayonetta/BayonettaDSmashStomp.gif"}],"move_name":"Down Smash","startup":"17/22","total_frames":"65","landing_lag":null,"notes":"First hit refers to Bayonetta's stomp and is ground only. Charge hold is frame 8.","base_damage":"5.0/16.0/15.0","shield_lag":"6/13/12","shield_stun":"4/11/10","which_hitbox":"Stomp/Early/Late","advantage":"\\-32","active_frames":"17—18/22(23—25)","hops_autocancel":null,"hops_actionable":null,"endlag":"40"}]},{"section_name":"Aerial Attacks","html_id":"aerialattacks","moves":[{"hitboxes":[{"name":null,"url":"https://ultimateframedata.com/hitboxes/bayonetta/BayonettaNAir.gif"}],"move_name":"Neutral Air","startup":"9","total_frames":"32","landing_lag":"10/18","notes":"Second landing lag is extended version. Autocancels on frame 34 onward","base_damage":"8.0/6.0/3.0","shield_lag":"7/6/5","shield_stun":"4/3/2","which_hitbox":"Early/Late/Extend","advantage":"\\-6/-7/-16","active_frames":"9—17(18—25) (full extended 26—66)","hops_autocancel":"SH, FH, FHFF","hops_actionable":"SH, FH, FHFF","endlag":null},{"hitboxes":[{"name":null,"url":"https://ultimateframedata.com/hitboxes/bayonetta/BayonettaFAir%201.gif"}],"move_name":"Forward Air 1","startup":"7","total_frames":"37","landing_lag":"12","notes":"Autocancels on frame 1-2 and 30 onward","base_damage":"4.0","shield_lag":"5","shield_stun":"5","which_hitbox":null,"advantage":"\\-7","active_frames":"7—9","hops_autocancel":"SH, FH, FHFF","hops_actionable":"SH, FH","endlag":"28"},{"hitboxes":[{"name":null,"url":"https://ultimateframedata.com/hitboxes/bayonetta/BayonettaFAir2.gif"}],"move_name":"Forward Air 2","startup":"7","total_frames":"39","landing_lag":"12","notes":"Autocancels on frame 32 onward","base_damage":"3.3","shield_lag":"5","shield_stun":"4","which_hitbox":null,"advantage":"\\-8","active_frames":"7—9","hops_autocancel":"SH, FH, FHFF","hops_actionable":"SH, FH","endlag":"30"},{"hitboxes":[{"name":null,"url":"https://ultimateframedata.com/hitboxes/bayonetta/BayonettaFAir3.gif"}],"move_name":"Forward Air 3","startup":"12","total_frames":"46","landing_lag":"12","notes":"Autocancels on frame 35 onward","base_damage":"7.0","shield_lag":"10","shield_stun":"7","which_hitbox":null,"advantage":"\\-5","active_frames":"12—15","hops_autocancel":"SH, FH, FHFF","hops_actionable":"FH","endlag":"31"},{"hitboxes":[{"name":null,"url":"https://ultimateframedata.com/hitboxes/bayonetta/BayonettaBAir.gif"}],"move_name":"Back Air","startup":"11","total_frames":"34","landing_lag":"10","notes":"Autocancels on frame 29 onward","base_damage":"13.0/10.0","shield_lag":"9/8","shield_stun":"5/4","which_hitbox":"Far/Close","advantage":"\\-5/-6","active_frames":"11—14","hops_autocancel":"SH, FH, FHFF","hops_actionable":"\\-, -","endlag":"20"},{"hitboxes":[{"name":null,"url":"https://ultimateframedata.com/hitboxes/bayonetta/BayonettaUAir.gif"}],"move_name":"Up Air","startup":"9","total_frames":"29","landing_lag":"8/16","notes":"Second landing lag is extended version. Autocancels on frame 1-2 and 26 onward","base_damage":"7.5/3.0","shield_lag":"7/5","shield_stun":"3/2","which_hitbox":"Normal/Extend","advantage":"\\-5/-14","active_frames":"9—18 (full extended 21—65)","hops_autocancel":"SH, FH, SHFF, FHFF","hops_actionable":"SH, FH, FHFF","endlag":null},{"hitboxes":[{"name":"Normal","url":"https://ultimateframedata.com/hitboxes/bayonetta/BayonettaDAir.gif"},{"name":"Landing","url":"https://ultimateframedata.com/hitboxes/bayonetta/BayonettaDAirLanding.gif"}],"move_name":"Down Air","startup":"18","total_frames":"52","landing_lag":"30","notes":"Landing hit on frame 1. Autocancels on frames 1-17 and 50 onward","base_damage":"7.0/8.0/9.0/5.0","shield_lag":"7/7/7/6","shield_stun":"3/3/4/6","which_hitbox":"Close/Far/Farther/Landing","advantage":"\\-23","active_frames":"18—24(25—35)/1—2","hops_autocancel":"FH","hops_actionable":"\\--","endlag":"17"}]},{"section_name":"Special Attacks","html_id":"specialattacks","moves":[{"hitboxes":[],"move_name":"Neutral B (Bullet Climax)","startup":"17/22/32/37","total_frames":"75","landing_lag":null,"notes":"Reaches full charge on 42. Can only shield cancel as early as frame 45. Repeated shots occur on the same pattern. Alternating 10 and 5 frames later.","base_damage":"1.3","shield_lag":"4","shield_stun":"2","which_hitbox":null,"advantage":"\\-32","active_frames":"17—26/22—31/32—41/37—46","hops_autocancel":null,"hops_actionable":null,"endlag":"29"},{"hitboxes":[],"move_name":"Neutral B, Full Charge (Bullet Climax, Full Charge)","startup":"42/47/57/62","total_frames":"100","landing_lag":null,"notes":"Repeated shots occur on the same pattern. Alternating 10 and 5 frames later.","base_damage":"2.7","shield_lag":"7","shield_stun":"2","which_hitbox":null,"advantage":"\\-29","active_frames":null,"hops_autocancel":null,"hops_actionable":null,"endlag":null},{"hitboxes":[{"name":"Normal","url":"https://ultimateframedata.com/hitboxes/bayonetta/BayonettaHeelSlide.gif"},{"name":"End","url":"https://ultimateframedata.com/hitboxes/bayonetta/BayonettaHeelSlideEnd.gif"}],"move_name":"Side B (Heel Slide)","startup":"15/51","total_frames":"66 (first) 67 (second)","landing_lag":null,"notes":"Second kick occurs only when button is held. Will not occur if first is blocked. 33 endlag when slide is blocked.","base_damage":"8.0/7.0/5.0","shield_lag":"7/7/6","shield_stun":"8/7/6","which_hitbox":"Early/Late/Second","advantage":"\\-25/-26/-15","active_frames":"15—16/17—18/19—24/25—39 first // 1—11/20—24 second","hops_autocancel":null,"hops_actionable":null,"endlag":"27"},{"hitboxes":[{"name":"Up","url":"https://ultimateframedata.com/hitboxes/bayonetta/BayonettaAfterburnerKickUp.gif"}],"move_name":"After Burner Kick","startup":"7","total_frames":"31","landing_lag":"20","notes":null,"base_damage":"6.0/7.0/6.0","shield_lag":"9/9/9","shield_stun":"6/7/6","which_hitbox":"Early/Late/Later","advantage":"\\-18","active_frames":"7-9/10-12/13-14/15-19","hops_autocancel":null,"hops_actionable":null,"endlag":"12"},{"hitboxes":[{"name":"Normal","url":"https://ultimateframedata.com/hitboxes/bayonetta/BayonettaAfterburnerKickDown.gif"},{"name":"Landing","url":"https://ultimateframedata.com/hitboxes/bayonetta/BayonettaAfterburnerKickLanding.gif"}],"move_name":"After Burner Kick, Down","startup":"8","total_frames":"43","landing_lag":"40","notes":"21 endlag on hit. Landing hit occurs on frame 1","base_damage":"6.5/5.0","shield_lag":"8/7","shield_stun":"7/6","which_hitbox":"Normal/Landing","advantage":"\\-14/-33","active_frames":"8—25/1","hops_autocancel":null,"hops_actionable":null,"endlag":"18"},{"hitboxes":[{"name":"First","url":"https://ultimateframedata.com/hitboxes/bayonetta/BayonettaWitchTwistG.gif"},{"name":"Second","url":"https://ultimateframedata.com/hitboxes/bayonetta/BayonettaWitchTwistA.gif"}],"move_name":"Up B (Witch Twist)","startup":"6/11...","total_frames":"31","landing_lag":"18","notes":"Both Grounded and Aerial versions are 1.0% weaker when used again.","base_damage":"3.0/0.2/3.0","shield_lag":"5/4/5","shield_stun":"4/2/4","which_hitbox":"First/Multi/Final","advantage":"\\+0","active_frames":"6/11—25(rehit: 3)/27—28","hops_autocancel":null,"hops_actionable":null,"endlag":"3"},{"hitboxes":[{"name":null,"url":"https://ultimateframedata.com/hitboxes/bayonetta/BayonettaWitchTime.gif"}],"move_name":"Down B (Witch Time)","startup":"8 (start of counter)","total_frames":"66","landing_lag":null,"notes":"Counters on frames 8—27. Intangible on 8—23, Bat Within 24—35 (overlaps with the Counter\nso 24—27 will trigger both Bat Within AND the slowdown).","base_damage":null,"shield_lag":null,"shield_stun":null,"which_hitbox":null,"advantage":null,"active_frames":"8—27 (counter)","hops_autocancel":null,"hops_actionable":null,"endlag":null}]},{"section_name":"Grabs / Throws","html_id":"grabs","moves":[{"hitboxes":[{"name":null,"url":"https://ultimateframedata.com/hitboxes/bayonetta/BayonettaGrab.gif"}],"move_name":"Grab","startup":"7","total_frames":"37","landing_lag":null,"notes":null,"base_damage":null,"shield_lag":null,"shield_stun":null,"which_hitbox":null,"advantage":null,"active_frames":"7—8","hops_autocancel":null,"hops_actionable":null,"endlag":"29"},{"hitboxes":[{"name":null,"url":"https://ultimateframedata.com/hitboxes/bayonetta/BayonettaDashGrab.gif"}],"move_name":"Dash Grab","startup":"10","total_frames":"45","landing_lag":null,"notes":null,"base_damage":null,"shield_lag":null,"shield_stun":null,"which_hitbox":null,"advantage":null,"active_frames":"10—11","hops_autocancel":null,"hops_actionable":null,"endlag":"34"},{"hitboxes":[{"name":null,"url":"https://ultimateframedata.com/hitboxes/bayonetta/BayonettaPivotGrab.gif"}],"move_name":"Pivot Grab","startup":"11","total_frames":"40","landing_lag":null,"notes":null,"base_damage":null,"shield_lag":null,"shield_stun":null,"which_hitbox":null,"advantage":null,"active_frames":"11—12","hops_autocancel":null,"hops_actionable":null,"endlag":"28"},{"hitboxes":[{"name":null,"url":"https://ultimateframedata.com/hitboxes/bayonetta/BayonettaPummel.gif"}],"move_name":"Pummel","startup":"1/13","total_frames":"25","landing_lag":null,"notes":"Startup and Total frames includes 19 frames of hitlag","base_damage":"0.6/0.7","shield_lag":null,"shield_stun":null,"which_hitbox":null,"advantage":null,"active_frames":null,"hops_autocancel":null,"hops_actionable":null,"endlag":null},{"hitboxes":[{"name":null,"url":"https://ultimateframedata.com/hitboxes/bayonetta/BayonettaFThrow.gif"}],"move_name":"Forward Throw","startup":"14/15","total_frames":"42","landing_lag":null,"notes":null,"base_damage":"7.0/3.0","shield_lag":null,"shield_stun":null,"which_hitbox":null,"advantage":null,"active_frames":null,"hops_autocancel":null,"hops_actionable":null,"endlag":null},{"hitboxes":[{"name":null,"url":"https://ultimateframedata.com/hitboxes/bayonetta/BayonettaBThrow.gif"}],"move_name":"Backward Throw","startup":"14-15","total_frames":"49","landing_lag":null,"notes":null,"base_damage":"3.0/6.0","shield_lag":null,"shield_stun":null,"which_hitbox":null,"advantage":null,"active_frames":null,"hops_autocancel":null,"hops_actionable":null,"endlag":null},{"hitboxes":[{"name":null,"url":"https://ultimateframedata.com/hitboxes/bayonetta/BayonettaUThrow.gif"}],"move_name":"Up Throw","startup":"9/10","total_frames":"35","landing_lag":null,"notes":null,"base_damage":"3.0/4.5","shield_lag":null,"shield_stun":null,"which_hitbox":null,"advantage":null,"active_frames":null,"hops_autocancel":null,"hops_actionable":null,"endlag":null},{"hitboxes":[{"name":null,"url":"https://ultimateframedata.com/hitboxes/bayonetta/BayonettaDThrow.gif"}],"move_name":"Down Throw","startup":"20/21","total_frames":"46","landing_lag":null,"notes":null,"base_damage":"3.0/5.0","shield_lag":null,"shield_stun":null,"which_hitbox":null,"advantage":null,"active_frames":null,"hops_autocancel":null,"hops_actionable":null,"endlag":null}]},{"section_name":"Dodges / Rolls","html_id":"dodges","moves":[{"hitboxes":[],"move_name":"Spot Dodge","startup":null,"total_frames":"20/25","landing_lag":null,"notes":"Intangible on frame 6-17. Bat within on frame 2-5.","base_damage":null,"shield_lag":null,"shield_stun":null,"which_hitbox":null,"advantage":null,"active_frames":null,"hops_autocancel":null,"hops_actionable":null,"endlag":null},{"hitboxes":[],"move_name":"Forward Roll","startup":null,"total_frames":"31","landing_lag":null,"notes":"Intangible on frame 6-15. Bat within on frame 2-5.","base_damage":null,"shield_lag":null,"shield_stun":null,"which_hitbox":null,"advantage":null,"active_frames":null,"hops_autocancel":null,"hops_actionable":null,"endlag":null},{"hitboxes":[],"move_name":"Backward Roll","startup":null,"total_frames":"36","landing_lag":null,"notes":"Intangible on frame 7-16. Bat within on frame 3-6.","base_damage":null,"shield_lag":null,"shield_stun":null,"which_hitbox":null,"advantage":null,"active_frames":null,"hops_autocancel":null,"hops_actionable":null,"endlag":null},{"hitboxes":[],"move_name":"Neutral Air Dodge","startup":null,"total_frames":"45","landing_lag":"10","notes":"Intangible on frame 5-31. Bat within on frame 1-4.","base_damage":null,"shield_lag":null,"shield_stun":null,"which_hitbox":null,"advantage":null,"active_frames":null,"hops_autocancel":null,"hops_actionable":null,"endlag":null},{"hitboxes":[],"move_name":"Air Dodge, Down","startup":null,"total_frames":"63","landing_lag":"11-19","notes":"Intangible on frame 5-21. Bat within on frame 1-4.","base_damage":null,"shield_lag":null,"shield_stun":null,"which_hitbox":null,"advantage":null,"active_frames":null,"hops_autocancel":null,"hops_actionable":null,"endlag":null},{"hitboxes":[],"move_name":"Air Dodge, Diagonally Down","startup":null,"total_frames":"69","landing_lag":"11-19","notes":"Intangible on frame 5-21. Bat within on frame 1-4.","base_damage":null,"shield_lag":null,"shield_stun":null,"which_hitbox":null,"advantage":null,"active_frames":null,"hops_autocancel":null,"hops_actionable":null,"endlag":null},{"hitboxes":[],"move_name":"Air Dodge, Left/Right","startup":null,"total_frames":"74","landing_lag":"11-19","notes":"Intangible on frame 5-21. Bat within on frame 1-4.","base_damage":null,"shield_lag":null,"shield_stun":null,"which_hitbox":null,"advantage":null,"active_frames":null,"hops_autocancel":null,"hops_actionable":null,"endlag":null},{"hitboxes":[],"move_name":"Air Dodge, Diagonally Up","startup":null,"total_frames":"85","landing_lag":"11-19","notes":"Intangible on frame 5-21. Bat within on frame 1-4.","base_damage":null,"shield_lag":null,"shield_stun":null,"which_hitbox":null,"advantage":null,"active_frames":null,"hops_autocancel":null,"hops_actionable":null,"endlag":null},{"hitboxes":[],"move_name":"Air Dodge, Up","startup":null,"total_frames":"93","landing_lag":"11-19","notes":"Intangible on frame 5-21. Bat within on frame 1-4.","base_damage":null,"shield_lag":null,"shield_stun":null,"which_hitbox":null,"advantage":null,"active_frames":null,"hops_autocancel":null,"hops_actionable":null,"endlag":null}]}],"misc_data":{"stats":{"weight":"81","gravity":"0.120","walk_speed":"0.945","run_speed":"1.76","initial_dash":"1.936","air_speed":"1.019","total_air_acceleration":"0.095","sh_fh_shff_fhff_frames":"38 / 50 / 27 / 35","fall_speed_fast_fall_speed":"1.77 / 2.832","oos_options":["Up B — 6 frames","Forward Air or Side B — 10 frames","Neutral Air or Up Air — 12 frames"],"shield_grab":"11 frames","shield_drop":"11 frames (universal)","jump_squat":"3 frames (universal)"},"moves":[{"hitboxes":[{"name":"Normal","url":"https://ultimateframedata.com/ledgegrabs/Bayonetta%20Ledgegrab%201.png"}],"move_name":"Ledge Grab","startup":null,"total_frames":null,"landing_lag":null,"notes":null,"base_damage":null,"shield_lag":null,"shield_stun":null,"which_hitbox":null,"advantage":null,"active_frames":null,"hops_autocancel":null,"hops_actionable":null,"endlag":null},{"hitboxes":[{"name":null,"url":"https://ultimateframedata.com/ledgehangs/Bayonetta%20Ledgehang.gif"}],"move_name":"Ledge Hang","startup":null,"total_frames":null,"landing_lag":null,"notes":null,"base_damage":null,"shield_lag":null,"shield_stun":null,"which_hitbox":null,"advantage":null,"active_frames":null,"hops_autocancel":null,"hops_actionable":null,"endlag":null},{"hitboxes":[{"name":"Facing Up","url":"https://ultimateframedata.com/hitboxes/bayonetta/bayonettaGetupAttackU.gif"},{"name":"Facing Down","url":"https://ultimateframedata.com/hitboxes/bayonetta/bayonettaGetupAttackD.gif"},{"name":"Trip","url":"https://ultimateframedata.com/hitboxes/bayonetta/bayonettaTripAttack.gif"},{"name":"Ledge","url":"https://ultimateframedata.com/hitboxes/bayonetta/bayonettaLedgeAttack.gif"}],"move_name":"Getup Attacks","startup":null,"total_frames":null,"landing_lag":null,"notes":null,"base_damage":null,"shield_lag":null,"shield_stun":null,"which_hitbox":null,"advantage":null,"active_frames":null,"hops_autocancel":null,"hops_actionable":null,"endlag":null}],"html_id":"misc"}}