{"ufd_url":"https://ultimateframedata.com/ike.php","name":"Ike","move_sections":[{"section_name":"Ground Attacks","html_id":"groundattacks","moves":[{"hitboxes":[{"name":null,"url":"https://ultimateframedata.com/hitboxes/ike/IkeJab1.gif"}],"move_name":"Jab 1","startup":"4","total_frames":"23","landing_lag":null,"notes":"Transitions to Jab 2 as early as frame 9","base_damage":"2.5","shield_lag":"8","shield_stun":"4","which_hitbox":null,"advantage":"\\-15","active_frames":"4—5","hops_autocancel":null,"hops_actionable":null,"endlag":"18"},{"hitboxes":[{"name":null,"url":"https://ultimateframedata.com/hitboxes/ike/IkeJab2.gif"}],"move_name":"Jab 2","startup":"3","total_frames":"27","landing_lag":null,"notes":"Transitions to jab 3 as early as frame 9","base_damage":"2.5","shield_lag":"6","shield_stun":"4","which_hitbox":null,"advantage":"\\-20","active_frames":"3—4","hops_autocancel":null,"hops_actionable":null,"endlag":"23"},{"hitboxes":[{"name":null,"url":"https://ultimateframedata.com/hitboxes/ike/IkeJab3.gif"}],"move_name":"Jab 3","startup":"5","total_frames":"40","landing_lag":null,"notes":"Attack hits directly above Ike on frame 5 only.","base_damage":"5.0","shield_lag":"12","shield_stun":"6","which_hitbox":null,"advantage":"\\-29","active_frames":"5—8","hops_autocancel":null,"hops_actionable":null,"endlag":"32"},{"hitboxes":[{"name":null,"url":"https://ultimateframedata.com/hitboxes/ike/IkeFTilt.gif"},{"name":null,"url":"https://ultimateframedata.com/hitboxes/ike/IkeFTiltUp.gif"},{"name":null,"url":"https://ultimateframedata.com/hitboxes/ike/IkeFTiltDown.gif"}],"move_name":"Forward Tilt","startup":"12","total_frames":"41","landing_lag":null,"notes":null,"base_damage":"12.5","shield_lag":"9","shield_stun":"12","which_hitbox":null,"advantage":"\\-17","active_frames":"12—13","hops_autocancel":null,"hops_actionable":null,"endlag":"28"},{"hitboxes":[{"name":null,"url":"https://ultimateframedata.com/hitboxes/ike/IkeUTilt.gif"}],"move_name":"Up Tilt","startup":"11","total_frames":"39","landing_lag":null,"notes":null,"base_damage":"12.0/8.0","shield_lag":"9","shield_stun":"11","which_hitbox":"Early/Late","advantage":"\\-17","active_frames":"11—16/17—21","hops_autocancel":null,"hops_actionable":null,"endlag":"18"},{"hitboxes":[{"name":null,"url":"https://ultimateframedata.com/hitboxes/ike/IkeDTilt.gif"}],"move_name":"Down Tilt","startup":"7","total_frames":"28","landing_lag":null,"notes":null,"base_damage":"8.0","shield_lag":"7","shield_stun":"8","which_hitbox":null,"advantage":"\\-13","active_frames":"7—8","hops_autocancel":null,"hops_actionable":null,"endlag":"20"},{"hitboxes":[{"name":null,"url":"https://ultimateframedata.com/hitboxes/ike/IkeDashAttack.gif"}],"move_name":"Dash Attack","startup":"15","total_frames":"47","landing_lag":null,"notes":null,"base_damage":"14.0","shield_lag":"12","shield_stun":"15","which_hitbox":null,"advantage":"\\-17","active_frames":"15—16/17—19","hops_autocancel":null,"hops_actionable":null,"endlag":"28"},{"hitboxes":[{"name":null,"url":"https://ultimateframedata.com/hitboxes/ike/IkeFSmash.gif"}],"move_name":"Forward Smash","startup":"31","total_frames":"83","landing_lag":null,"notes":"Sword hits directly above Ike on frame 31. Strong hit on 33. Charge hold is frame 24","base_damage":"19.0/22.0","shield_lag":"12/13","shield_stun":"13/14","which_hitbox":"Early/Late","advantage":"\\-39/-36","active_frames":"31—32/33—35","hops_autocancel":null,"hops_actionable":null,"endlag":"48"},{"hitboxes":[{"name":null,"url":"https://ultimateframedata.com/hitboxes/ike/IkeUSmash.gif"}],"move_name":"Up Smash","startup":"25","total_frames":"70","landing_lag":null,"notes":"Charge hold is frame 11","base_damage":"17.0/10.0","shield_lag":"11","shield_stun":"11","which_hitbox":"Early/Late","advantage":"\\-34","active_frames":"25—29/30—31","hops_autocancel":null,"hops_actionable":null,"endlag":"39"},{"hitboxes":[{"name":null,"url":"https://ultimateframedata.com/hitboxes/ike/IkeDSmash.gif"}],"move_name":"Down Smash","startup":"13/32","total_frames":"70","landing_lag":null,"notes":"Charge hold is frame 5","base_damage":"16.0/19.0/9","shield_lag":"10/12/\\*\\*","shield_stun":"11/13/\\*\\*","which_hitbox":"First/Second/Second Late","advantage":"\\-46/-25","active_frames":"13—15/32—33/34—36","hops_autocancel":null,"hops_actionable":null,"endlag":"34"}]},{"section_name":"Aerial Attacks","html_id":"aerialattacks","moves":[{"hitboxes":[{"name":null,"url":"https://ultimateframedata.com/hitboxes/ike/IkeNAir.gif"}],"move_name":"Neutral Air","startup":"10","total_frames":"59","landing_lag":"8","notes":"Autocancels on frame 1-2 and 50 onward","base_damage":"7.5/6.0","shield_lag":"7/6","shield_stun":"3/3","which_hitbox":"Early/Late","advantage":"\\-5","active_frames":"10—14/15—22","hops_autocancel":"\\--","hops_actionable":"\\--","endlag":"37"},{"hitboxes":[{"name":null,"url":"https://ultimateframedata.com/hitboxes/ike/IkeFAir.gif"}],"move_name":"Forward Air","startup":"11","total_frames":"51","landing_lag":"14","notes":"Autocancels on frame 42 onward","base_damage":"13.0","shield_lag":"9","shield_stun":"5","which_hitbox":null,"advantage":"\\-9","active_frames":"11—15","hops_autocancel":"FH","hops_actionable":"\\--","endlag":"36"},{"hitboxes":[{"name":null,"url":"https://ultimateframedata.com/hitboxes/ike/IkeBAir.gif"}],"move_name":"Back Air","startup":"7","total_frames":"54","landing_lag":"11","notes":"Autocancels on frame 1-2 and 35 onward","base_damage":"14.0","shield_lag":"10","shield_stun":"5","which_hitbox":null,"advantage":"\\-6","active_frames":"7—9","hops_autocancel":"SH, FH","hops_actionable":"\\--","endlag":"45"},{"hitboxes":[{"name":null,"url":"https://ultimateframedata.com/hitboxes/ike/IkeUAir.gif"}],"move_name":"Up Air","startup":"13","total_frames":"56","landing_lag":"9","notes":"Autocancels on frame 1-5 and 51 onward","base_damage":"11.0","shield_lag":"8","shield_stun":"4","which_hitbox":null,"advantage":"\\-5","active_frames":"13—18","hops_autocancel":"\\--","hops_actionable":"\\--","endlag":"38"},{"hitboxes":[{"name":null,"url":"https://ultimateframedata.com/hitboxes/ike/IkeDAir.gif"}],"move_name":"Down Air","startup":"16","total_frames":"54","landing_lag":"14","notes":"Autocancels on frame 1-4 and 48 onward","base_damage":"15.0","shield_lag":"10","shield_stun":"5","which_hitbox":null,"advantage":"\\-9","active_frames":"16—17","hops_autocancel":"FH","hops_actionable":"\\--","endlag":"37"}]},{"section_name":"Special Attacks","html_id":"specialattacks","moves":[{"hitboxes":[{"name":"No Charge","url":"https://ultimateframedata.com/hitboxes/ike/IkeEruption.gif"},{"name":"Mid Charge","url":"https://ultimateframedata.com/hitboxes/ike/IkeEruptionMid.gif"},{"name":"Max Charge","url":"https://ultimateframedata.com/hitboxes/ike/IkeEruptionMax.gif"}],"move_name":"Neutral B (Eruption)","startup":"30-239","total_frames":"78-287","landing_lag":null,"notes":"On release, startup is 11 and total frames is 59","base_damage":"10.0—35.0","shield_lag":"8—16","shield_stun":"10—Shieldbreak","which_hitbox":null,"advantage":"\\-38 to Shieldbreak","active_frames":null,"hops_autocancel":null,"hops_actionable":null,"endlag":null},{"hitboxes":[{"name":"Hit","url":"https://ultimateframedata.com/hitboxes/ike/IkeQuickDraw.gif"},{"name":"Detection","url":"https://ultimateframedata.com/hitboxes/ike/IkeQuickDrawDash.gif"}],"move_name":"Side B (Quickdraw)","startup":"16","total_frames":"53/34/44","landing_lag":"30","notes":"Reaches max charge around 85. Startup is 2 upon reaching a target. Swing total frames is 34, or 44 from the air. Landing lag only occurs after entering special fall. Can continue recovery options after an air swing on frame 44.","base_damage":"6.0—13.0","shield_lag":"6—9","shield_stun":"6—12","which_hitbox":null,"advantage":"\\-28 to -22","active_frames":null,"hops_autocancel":null,"hops_actionable":null,"endlag":null},{"hitboxes":[{"name":"Ground","url":"https://ultimateframedata.com/hitboxes/ike/IkeAetherG.gif"},{"name":"Air","url":"https://ultimateframedata.com/hitboxes/ike/IkeAetherA.gif"},{"name":"Falling","url":"https://ultimateframedata.com/hitboxes/ike/IkeAetherFall.gif"},{"name":"Landing","url":"https://ultimateframedata.com/hitboxes/ike/IkeAetherLanding.gif"},{"name":"Sword","url":"https://ultimateframedata.com/hitboxes/ike/IkeAetherSword.gif"}],"move_name":"Up B (Aether)","startup":"15/44/51/61","total_frames":null,"landing_lag":"36","notes":"Landing hit on frame 1. Super armor on frame 5-35. (ending the frame he ascends). Super armor on frame 15-35 for the air version.","base_damage":"6.0/1.0/3.0/6.0","shield_lag":"6/4/5/6","shield_stun":"6/2/4/6","which_hitbox":"First/multi/falling/landing","advantage":"\\-29","active_frames":null,"hops_autocancel":null,"hops_actionable":null,"endlag":null},{"hitboxes":[{"name":null,"url":"https://ultimateframedata.com/hitboxes/ike/IkeCounter.gif"}],"move_name":"Down B (Counter)","startup":"9 (Start of Counter)","total_frames":"73","landing_lag":null,"notes":"Invulnerable on frame 8. Counters on frame 9-33","base_damage":null,"shield_lag":null,"shield_stun":null,"which_hitbox":null,"advantage":null,"active_frames":null,"hops_autocancel":null,"hops_actionable":null,"endlag":null},{"hitboxes":[{"name":null,"url":"https://ultimateframedata.com/hitboxes/ike/IkeCounterHit.gif"}],"move_name":"Counter, Attack","startup":"4","total_frames":"43","landing_lag":null,"notes":"Invulnerable on frame 1-4 in addition to counter freeze frames","base_damage":null,"shield_lag":null,"shield_stun":null,"which_hitbox":null,"advantage":null,"active_frames":"4—5","hops_autocancel":null,"hops_actionable":null,"endlag":"38"}]},{"section_name":"Grabs / Throws","html_id":"grabs","moves":[{"hitboxes":[{"name":null,"url":"https://ultimateframedata.com/hitboxes/ike/IkeGrab.gif"}],"move_name":"Grab","startup":"7","total_frames":"36","landing_lag":null,"notes":null,"base_damage":null,"shield_lag":null,"shield_stun":null,"which_hitbox":null,"advantage":null,"active_frames":"7—8","hops_autocancel":null,"hops_actionable":null,"endlag":"28"},{"hitboxes":[{"name":null,"url":"https://ultimateframedata.com/hitboxes/ike/IkeDashGrab.gif"}],"move_name":"Dash Grab","startup":"10","total_frames":"44","landing_lag":null,"notes":null,"base_damage":null,"shield_lag":null,"shield_stun":null,"which_hitbox":null,"advantage":null,"active_frames":"10—11","hops_autocancel":null,"hops_actionable":null,"endlag":"33"},{"hitboxes":[{"name":null,"url":"https://ultimateframedata.com/hitboxes/ike/IkePivotGrab.gif"}],"move_name":"Pivot Grab","startup":"11","total_frames":"39","landing_lag":null,"notes":null,"base_damage":null,"shield_lag":null,"shield_stun":null,"which_hitbox":null,"advantage":null,"active_frames":"11—12","hops_autocancel":null,"hops_actionable":null,"endlag":"27"},{"hitboxes":[{"name":null,"url":"https://ultimateframedata.com/hitboxes/ike/IkePummel.gif"}],"move_name":"Pummel","startup":"1","total_frames":"20","landing_lag":"Total frames includes 14 frames of hitlag.","notes":null,"base_damage":"1.6","shield_lag":null,"shield_stun":null,"which_hitbox":null,"advantage":null,"active_frames":null,"hops_autocancel":null,"hops_actionable":null,"endlag":null},{"hitboxes":[{"name":null,"url":"https://ultimateframedata.com/hitboxes/ike/IkeFThrow.gif"}],"move_name":"Forward Throw","startup":"5/8","total_frames":"32","landing_lag":null,"notes":null,"base_damage":"3.5/4.0","shield_lag":null,"shield_stun":null,"which_hitbox":null,"advantage":null,"active_frames":null,"hops_autocancel":null,"hops_actionable":null,"endlag":null},{"hitboxes":[{"name":null,"url":"https://ultimateframedata.com/hitboxes/ike/IkeBThrow.gif"}],"move_name":"Backward Throw","startup":"20/22","total_frames":"37","landing_lag":null,"notes":null,"base_damage":"3.0/4.0","shield_lag":null,"shield_stun":null,"which_hitbox":null,"advantage":null,"active_frames":null,"hops_autocancel":null,"hops_actionable":null,"endlag":null},{"hitboxes":[{"name":null,"url":"https://ultimateframedata.com/hitboxes/ike/IkeUThrow.gif"}],"move_name":"Up Throw","startup":"18/20","total_frames":"42","landing_lag":null,"notes":null,"base_damage":"3.5/4.0","shield_lag":null,"shield_stun":null,"which_hitbox":null,"advantage":null,"active_frames":null,"hops_autocancel":null,"hops_actionable":null,"endlag":null},{"hitboxes":[{"name":null,"url":"https://ultimateframedata.com/hitboxes/ike/IkeDThrow.gif"}],"move_name":"Down Throw","startup":"35/40","total_frames":"57","landing_lag":null,"notes":null,"base_damage":"3.0/4.0","shield_lag":null,"shield_stun":null,"which_hitbox":null,"advantage":null,"active_frames":null,"hops_autocancel":null,"hops_actionable":null,"endlag":null}]},{"section_name":"Dodges / Rolls","html_id":"dodges","moves":[{"hitboxes":[],"move_name":"Spot Dodge","startup":null,"total_frames":"21/26","landing_lag":null,"notes":"Intangible on frame 3-17","base_damage":null,"shield_lag":null,"shield_stun":null,"which_hitbox":null,"advantage":null,"active_frames":null,"hops_autocancel":null,"hops_actionable":null,"endlag":null},{"hitboxes":[],"move_name":"Forward Roll","startup":null,"total_frames":"30","landing_lag":null,"notes":"Intangible on frame 4-15.","base_damage":null,"shield_lag":null,"shield_stun":null,"which_hitbox":null,"advantage":null,"active_frames":null,"hops_autocancel":null,"hops_actionable":null,"endlag":null},{"hitboxes":[],"move_name":"Backward Roll","startup":null,"total_frames":"35","landing_lag":null,"notes":"Intangible on frame 5-16.","base_damage":null,"shield_lag":null,"shield_stun":null,"which_hitbox":null,"advantage":null,"active_frames":null,"hops_autocancel":null,"hops_actionable":null,"endlag":null},{"hitboxes":[],"move_name":"Neutral Air Dodge","startup":null,"total_frames":"49","landing_lag":"10","notes":"Intangible on frame 4-31.","base_damage":null,"shield_lag":null,"shield_stun":null,"which_hitbox":null,"advantage":null,"active_frames":null,"hops_autocancel":null,"hops_actionable":null,"endlag":null},{"hitboxes":[],"move_name":"Air Dodge, Down","startup":null,"total_frames":"66","landing_lag":"11-19","notes":"Intangible on frame 4-22.","base_damage":null,"shield_lag":null,"shield_stun":null,"which_hitbox":null,"advantage":null,"active_frames":null,"hops_autocancel":null,"hops_actionable":null,"endlag":null},{"hitboxes":[],"move_name":"Air Dodge, Diagonally Down","startup":null,"total_frames":"76","landing_lag":"11-19","notes":"Intangible on frame 4-22.","base_damage":null,"shield_lag":null,"shield_stun":null,"which_hitbox":null,"advantage":null,"active_frames":null,"hops_autocancel":null,"hops_actionable":null,"endlag":null},{"hitboxes":[],"move_name":"Air Dodge, Left/Right","startup":null,"total_frames":"82","landing_lag":"11-19","notes":"Intangible on frame 4-22.","base_damage":null,"shield_lag":null,"shield_stun":null,"which_hitbox":null,"advantage":null,"active_frames":null,"hops_autocancel":null,"hops_actionable":null,"endlag":null},{"hitboxes":[],"move_name":"Air Dodge, Diagonally Up","startup":null,"total_frames":"96","landing_lag":"11-19","notes":"Intangible on frame 4-22.","base_damage":null,"shield_lag":null,"shield_stun":null,"which_hitbox":null,"advantage":null,"active_frames":null,"hops_autocancel":null,"hops_actionable":null,"endlag":null},{"hitboxes":[],"move_name":"Air Dodge, Up","startup":null,"total_frames":"108","landing_lag":"11-19","notes":"Intangible on frame 4-22.","base_damage":null,"shield_lag":null,"shield_stun":null,"which_hitbox":null,"advantage":null,"active_frames":null,"hops_autocancel":null,"hops_actionable":null,"endlag":null}]}],"misc_data":{"stats":{"weight":"107","gravity":"0.092","walk_speed":"0.912","run_speed":"1.507","initial_dash":"1.815","air_speed":"1.134","total_air_acceleration":"0.05","sh_fh_shff_fhff_frames":"37 / 48 / 26 / 33","fall_speed_fast_fall_speed":"1.65 / 2.64","oos_options":["Back Air — 10 frames","Neutral Air — 13 frames","Forward Air — 14 frames","Up B — 15 frames (but armor starts on frame 5)"],"shield_grab":"11 frames","shield_drop":"11 frames (universal)","jump_squat":"3 frames (universal)"},"moves":[{"hitboxes":[{"name":"Normal","url":"https://ultimateframedata.com/ledgegrabs/Ike%20Ledgegrab%201.png"}],"move_name":"Ledge Grab","startup":null,"total_frames":null,"landing_lag":null,"notes":null,"base_damage":null,"shield_lag":null,"shield_stun":null,"which_hitbox":null,"advantage":null,"active_frames":null,"hops_autocancel":null,"hops_actionable":null,"endlag":null},{"hitboxes":[{"name":null,"url":"https://ultimateframedata.com/ledgehangs/Ike%20Ledgehang.gif"}],"move_name":"Ledge Hang","startup":null,"total_frames":null,"landing_lag":null,"notes":null,"base_damage":null,"shield_lag":null,"shield_stun":null,"which_hitbox":null,"advantage":null,"active_frames":null,"hops_autocancel":null,"hops_actionable":null,"endlag":null},{"hitboxes":[{"name":"Facing Up","url":"https://ultimateframedata.com/hitboxes/ike/ikeGetupAttackU.gif"},{"name":"Facing Down","url":"https://ultimateframedata.com/hitboxes/ike/ikeGetupAttackD.gif"},{"name":"Trip","url":"https://ultimateframedata.com/hitboxes/ike/ikeTripAttack.gif"},{"name":"Ledge","url":"https://ultimateframedata.com/hitboxes/ike/ikeLedgeAttack.gif"}],"move_name":"Getup Attacks","startup":null,"total_frames":null,"landing_lag":null,"notes":null,"base_damage":null,"shield_lag":null,"shield_stun":null,"which_hitbox":null,"advantage":null,"active_frames":null,"hops_autocancel":null,"hops_actionable":null,"endlag":null}],"html_id":"misc"}}